faq/__init__.py
faq/admin.py
faq/apps.py
faq/static/css/faq/bethany_ds.css
faq/static/css/faq/medicio_ds.css
faq/static/css/faq/medilab_ds.css
faq/static/css/faq/mentor_ds.css
faq/templates/faq/_common.html
faq/templates/faq/bethany_ds.html
faq/templates/faq/medicio_ds.html
faq/templates/faq/medilab_ds.html
faq/templates/faq/mentor_ds.html
faq/templatetags/__init__.py
faq/templatetags/faq_tags.py
django_faq_ds-1.2.1.dist-info/LICENSE
django_faq_ds-1.2.1.dist-info/METADATA
django_faq_ds-1.2.1.dist-info/WHEEL
django_faq_ds-1.2.1.dist-info/top_level.txt
django_faq_ds-1.2.1.dist-info/RECORD
